<keymap version="1" name="GNOME copy" parent="Default for GNOME">
  <action id="ActivateProjectToolWindow">
    <keyboard-shortcut first-keystroke="alt 1" />
    <keyboard-shortcut first-keystroke="alt ampersand" />
  </action>
  <action id="ActivateTerminalToolWindow">
    <keyboard-shortcut first-keystroke="alt f12" />
    <keyboard-shortcut first-keystroke="alt a" />
  </action>
  <action id="CommentByLineComment">
    <keyboard-shortcut first-keystroke="ctrl slash" />
    <keyboard-shortcut first-keystroke="ctrl divide" />
    <keyboard-shortcut first-keystroke="ctrl colon" />
  </action>
  <action id="EditorCodeBlockEnd">
    <keyboard-shortcut first-keystroke="ctrl close_bracket" />
    <keyboard-shortcut first-keystroke="ctrl down" />
  </action>
  <action id="EditorCodeBlockEndWithSelection">
    <keyboard-shortcut first-keystroke="shift ctrl close_bracket" />
    <keyboard-shortcut first-keystroke="shift ctrl down" />
  </action>
  <action id="EditorCodeBlockStart">
    <keyboard-shortcut first-keystroke="ctrl open_bracket" />
    <keyboard-shortcut first-keystroke="ctrl up" />
  </action>
  <action id="EditorCodeBlockStartWithSelection">
    <keyboard-shortcut first-keystroke="shift ctrl open_bracket" />
    <keyboard-shortcut first-keystroke="shift ctrl down" />
    <keyboard-shortcut first-keystroke="shift ctrl up" />
  </action>
  <action id="EditorLineEnd">
    <keyboard-shortcut first-keystroke="end" />
    <keyboard-shortcut first-keystroke="ctrl right" />
  </action>
  <action id="EditorLineEndWithSelection">
    <keyboard-shortcut first-keystroke="shift end" />
    <keyboard-shortcut first-keystroke="shift ctrl right" />
  </action>
  <action id="EditorLineStart">
    <keyboard-shortcut first-keystroke="home" />
    <keyboard-shortcut first-keystroke="ctrl left" />
  </action>
  <action id="EditorLineStartWithSelection">
    <keyboard-shortcut first-keystroke="shift home" />
    <keyboard-shortcut first-keystroke="shift ctrl left" />
  </action>
  <action id="EditorLookupDown" />
  <action id="EditorLookupUp" />
  <action id="EditorNextWord" />
  <action id="EditorNextWordWithSelection" />
  <action id="EditorPreviousWord" />
  <action id="EditorPreviousWordWithSelection" />
  <action id="EditorScrollDown" />
  <action id="EditorScrollUp" />
  <action id="ExpressionTypeInfo" />
  <action id="FindPrevious">
    <keyboard-shortcut first-keystroke="shift f3" />
  </action>
  <action id="GotoFile">
    <keyboard-shortcut first-keystroke="shift ctrl n" />
    <keyboard-shortcut first-keystroke="shift ctrl p" />
  </action>
  <action id="MethodOverloadSwitchDown" />
  <action id="MethodOverloadSwitchUp" />
  <action id="MoveStatementDown" />
  <action id="MoveStatementUp" />
  <action id="SearchEverywhere.NavigateToNextGroup">
    <keyboard-shortcut first-keystroke="page_down" />
  </action>
  <action id="SearchEverywhere.NavigateToPrevGroup">
    <keyboard-shortcut first-keystroke="page_up" />
  </action>
  <action id="SelectNextOccurrence">
    <keyboard-shortcut first-keystroke="alt j" />
    <keyboard-shortcut first-keystroke="shift ctrl l" />
  </action>
  <action id="Terminal.ClearBuffer" />
  <action id="Vcs.Log.FocusTextFilter" />
  <action id="Vcs.Show.Local.Changes">
    <keyboard-shortcut first-keystroke="alt #10000e9" />
  </action>
</keymap>